LICENSE
MANIFEST.in
README.md
setup.py
docs/_build/html/_static/ajax-loader.gif
docs/_build/html/_static/comment-bright.png
docs/_build/html/_static/comment-close.png
docs/_build/html/_static/comment.png
docs/_build/html/_static/down-pressed.png
docs/_build/html/_static/down.png
docs/_build/html/_static/file.png
docs/_build/html/_static/minus.png
docs/_build/html/_static/plus.png
docs/_build/html/_static/up-pressed.png
docs/_build/html/_static/up.png
pyprimed/__init__.py
pyprimed/api.py
pyprimed/const.py
pyprimed/exceptions.py
pyprimed/pio.py
pyprimed/piospark.py
pyprimed/util.py
pyprimed.egg-info/PKG-INFO
pyprimed.egg-info/SOURCES.txt
pyprimed.egg-info/dependency_links.txt
pyprimed.egg-info/not-zip-safe
pyprimed.egg-info/requires.txt
pyprimed.egg-info/top_level.txt
pyprimed/models/__init__.py
pyprimed/models/abvariant.py
pyprimed/models/abvariants.py
pyprimed/models/apikey.py
pyprimed/models/apikeys.py
pyprimed/models/base.py
pyprimed/models/campaign.py
pyprimed/models/campaigns.py
pyprimed/models/experiment.py
pyprimed/models/experiments.py
pyprimed/models/model.py
pyprimed/models/models.py
pyprimed/models/personalise_result_wrapper.py
pyprimed/models/prediction.py
pyprimed/models/predictions.py
pyprimed/models/resultset.py
pyprimed/models/signal.py
pyprimed/models/signals.py
pyprimed/models/target.py
pyprimed/models/targets.py
pyprimed/models/universe.py
pyprimed/models/universes.py
pyprimed/models/user.py
pyprimed/models/users.py
tests/conftest.py
tests/test_collection.py
tests/test_hierarchyhelper.py
tests/test_methods.py
tests/test_personalise.py
tests/test_relationshipcollection.py
tests/test_request.py
tests/test_resource.py
tests/test_result_set.py
tests/test_util.py
tests/samples/personalise_response.json