Metadata-Version: 2.1
Name: pyprimed
Version: 2.1.8
Summary: Python client to manage PrimedIO
Home-page: https://gitlab.com/primedio/delivery-pyprimed
Author: Matthijs van der Kroon
Author-email: matthijs@primed.io
License: Apache Software License 2.0
Keywords: pyprimed primedio
Platform: UNKNOWN
Classifier: Development Status :: 2 - Pre-Alpha
Classifier: Intended Audience :: Developers
Classifier: License :: OSI Approved :: Apache Software License
Classifier: Natural Language :: English
Classifier: Programming Language :: Python :: 3.4
Classifier: Programming Language :: Python :: 3.5
Classifier: Programming Language :: Python :: 3.6
